{
	"inputs" : 
	[
		{
			"path" : "CMakeLists.txt"
		},
		{
			"isGenerated" : true,
			"path" : "cmake-build-debug/CMakeFiles/3.30.5/CMakeSystem.cmake"
		},
		{
			"isCMake" : true,
			"isExternal" : true,
			"path" : "/home/tim/clion/clion-2024.3/bin/cmake/linux/x64/share/cmake-3.30/Modules/CMakeSystemSpecificInitialize.cmake"
		},
		{
			"isCMake" : true,
			"isExternal" : true,
			"path" : "/home/tim/clion/clion-2024.3/bin/cmake/linux/x64/share/cmake-3.30/Modules/Platform/Linux-Initialize.cmake"
		},
		{
			"isGenerated" : true,
			"path" : "cmake-build-debug/CMakeFiles/3.30.5/CMakeCXXCompiler.cmake"
		},
		{
			"isCMake" : true,
			"isExternal" : true,
			"path" : "/home/tim/clion/clion-2024.3/bin/cmake/linux/x64/share/cmake-3.30/Modules/CMakeSystemSpecificInformation.cmake"
		},
		{
			"isCMake" : true,
			"isExternal" : true,
			"path" : "/home/tim/clion/clion-2024.3/bin/cmake/linux/x64/share/cmake-3.30/Modules/CMakeGenericSystem.cmake"
		},
		{
			"isCMake" : true,
			"isExternal" : true,
			"path" : "/home/tim/clion/clion-2024.3/bin/cmake/linux/x64/share/cmake-3.30/Modules/CMakeInitializeConfigs.cmake"
		},
		{
			"isCMake" : true,
			"isExternal" : true,
			"path" : "/home/tim/clion/clion-2024.3/bin/cmake/linux/x64/share/cmake-3.30/Modules/Platform/Linux.cmake"
		},
		{
			"isCMake" : true,
			"isExternal" : true,
			"path" : "/home/tim/clion/clion-2024.3/bin/cmake/linux/x64/share/cmake-3.30/Modules/Platform/UnixPaths.cmake"
		},
		{
			"isCMake" : true,
			"isExternal" : true,
			"path" : "/home/tim/clion/clion-2024.3/bin/cmake/linux/x64/share/cmake-3.30/Modules/CMakeCXXInformation.cmake"
		},
		{
			"isCMake" : true,
			"isExternal" : true,
			"path" : "/home/tim/clion/clion-2024.3/bin/cmake/linux/x64/share/cmake-3.30/Modules/CMakeLanguageInformation.cmake"
		},
		{
			"isCMake" : true,
			"isExternal" : true,
			"path" : "/home/tim/clion/clion-2024.3/bin/cmake/linux/x64/share/cmake-3.30/Modules/Compiler/GNU-CXX.cmake"
		},
		{
			"isCMake" : true,
			"isExternal" : true,
			"path" : "/home/tim/clion/clion-2024.3/bin/cmake/linux/x64/share/cmake-3.30/Modules/Compiler/GNU.cmake"
		},
		{
			"isCMake" : true,
			"isExternal" : true,
			"path" : "/home/tim/clion/clion-2024.3/bin/cmake/linux/x64/share/cmake-3.30/Modules/Compiler/CMakeCommonCompilerMacros.cmake"
		},
		{
			"isCMake" : true,
			"isExternal" : true,
			"path" : "/home/tim/clion/clion-2024.3/bin/cmake/linux/x64/share/cmake-3.30/Modules/Platform/Linux-GNU-CXX.cmake"
		},
		{
			"isCMake" : true,
			"isExternal" : true,
			"path" : "/home/tim/clion/clion-2024.3/bin/cmake/linux/x64/share/cmake-3.30/Modules/Platform/Linux-GNU.cmake"
		},
		{
			"isCMake" : true,
			"isExternal" : true,
			"path" : "/home/tim/clion/clion-2024.3/bin/cmake/linux/x64/share/cmake-3.30/Modules/CMakeCommonLanguageInclude.cmake"
		},
		{
			"isCMake" : true,
			"isExternal" : true,
			"path" : "/home/tim/clion/clion-2024.3/bin/cmake/linux/x64/share/cmake-3.30/Modules/FetchContent.cmake"
		},
		{
			"isCMake" : true,
			"isExternal" : true,
			"path" : "/home/tim/clion/clion-2024.3/bin/cmake/linux/x64/share/cmake-3.30/Modules/ExternalProject/shared_internal_commands.cmake"
		},
		{
			"isCMake" : true,
			"isExternal" : true,
			"path" : "/home/tim/clion/clion-2024.3/bin/cmake/linux/x64/share/cmake-3.30/Modules/FindGit.cmake"
		},
		{
			"isCMake" : true,
			"isExternal" : true,
			"path" : "/home/tim/clion/clion-2024.3/bin/cmake/linux/x64/share/cmake-3.30/Modules/FindPackageHandleStandardArgs.cmake"
		},
		{
			"isCMake" : true,
			"isExternal" : true,
			"path" : "/home/tim/clion/clion-2024.3/bin/cmake/linux/x64/share/cmake-3.30/Modules/FindPackageMessage.cmake"
		},
		{
			"isCMake" : true,
			"isExternal" : true,
			"path" : "/home/tim/clion/clion-2024.3/bin/cmake/linux/x64/share/cmake-3.30/Modules/FetchContent/CMakeLists.cmake.in"
		},
		{
			"path" : "cmake/version.hpp.in"
		},
		{
			"isCMake" : true,
			"isExternal" : true,
			"path" : "/home/tim/clion/clion-2024.3/bin/cmake/linux/x64/share/cmake-3.30/Modules/CMakePackageConfigHelpers.cmake"
		},
		{
			"isCMake" : true,
			"isExternal" : true,
			"path" : "/home/tim/clion/clion-2024.3/bin/cmake/linux/x64/share/cmake-3.30/Modules/WriteBasicConfigVersionFile.cmake"
		},
		{
			"isCMake" : true,
			"isExternal" : true,
			"path" : "/home/tim/clion/clion-2024.3/bin/cmake/linux/x64/share/cmake-3.30/Modules/BasicConfigVersion-AnyNewerVersion.cmake.in"
		},
		{
			"path" : "cmake/CLUEsteringConfig.cmake.in"
		},
		{
			"isGenerated" : true,
			"path" : "cmake-build-debug/_deps/alpaka-src/CMakeLists.txt"
		},
		{
			"isGenerated" : true,
			"path" : "cmake-build-debug/CMakeFiles/3.30.5/CMakeCCompiler.cmake"
		},
		{
			"isCMake" : true,
			"isExternal" : true,
			"path" : "/home/tim/clion/clion-2024.3/bin/cmake/linux/x64/share/cmake-3.30/Modules/CMakeCInformation.cmake"
		},
		{
			"isCMake" : true,
			"isExternal" : true,
			"path" : "/home/tim/clion/clion-2024.3/bin/cmake/linux/x64/share/cmake-3.30/Modules/CMakeLanguageInformation.cmake"
		},
		{
			"isCMake" : true,
			"isExternal" : true,
			"path" : "/home/tim/clion/clion-2024.3/bin/cmake/linux/x64/share/cmake-3.30/Modules/Compiler/GNU-C.cmake"
		},
		{
			"isCMake" : true,
			"isExternal" : true,
			"path" : "/home/tim/clion/clion-2024.3/bin/cmake/linux/x64/share/cmake-3.30/Modules/Compiler/GNU.cmake"
		},
		{
			"isCMake" : true,
			"isExternal" : true,
			"path" : "/home/tim/clion/clion-2024.3/bin/cmake/linux/x64/share/cmake-3.30/Modules/Platform/Linux-GNU-C.cmake"
		},
		{
			"isCMake" : true,
			"isExternal" : true,
			"path" : "/home/tim/clion/clion-2024.3/bin/cmake/linux/x64/share/cmake-3.30/Modules/Platform/Linux-GNU.cmake"
		},
		{
			"isCMake" : true,
			"isExternal" : true,
			"path" : "/home/tim/clion/clion-2024.3/bin/cmake/linux/x64/share/cmake-3.30/Modules/CMakeCommonLanguageInclude.cmake"
		},
		{
			"isGenerated" : true,
			"path" : "cmake-build-debug/_deps/alpaka-src/cmake/alpakaCommon.cmake"
		},
		{
			"isGenerated" : true,
			"path" : "cmake-build-debug/_deps/alpaka-src/cmake/buildDependencies.cmake"
		},
		{
			"isGenerated" : true,
			"path" : "cmake-build-debug/_deps/alpaka-src/cmake/finalize.cmake"
		},
		{
			"isGenerated" : true,
			"path" : "cmake-build-debug/_deps/alpaka-src/cmake/common.cmake"
		},
		{
			"isCMake" : true,
			"isExternal" : true,
			"path" : "/home/tim/clion/clion-2024.3/bin/cmake/linux/x64/share/cmake-3.30/Modules/CheckLanguage.cmake"
		},
		{
			"isCMake" : true,
			"isExternal" : true,
			"path" : "/home/tim/clion/clion-2024.3/bin/cmake/linux/x64/share/cmake-3.30/Modules/FindOpenMP.cmake"
		},
		{
			"isCMake" : true,
			"isExternal" : true,
			"path" : "/home/tim/clion/clion-2024.3/bin/cmake/linux/x64/share/cmake-3.30/Modules/CMakeParseImplicitLinkInfo.cmake"
		},
		{
			"isCMake" : true,
			"isExternal" : true,
			"path" : "/home/tim/clion/clion-2024.3/bin/cmake/linux/x64/share/cmake-3.30/Modules/FindPackageHandleStandardArgs.cmake"
		},
		{
			"isCMake" : true,
			"isExternal" : true,
			"path" : "/home/tim/clion/clion-2024.3/bin/cmake/linux/x64/share/cmake-3.30/Modules/FindPackageMessage.cmake"
		},
		{
			"isGenerated" : true,
			"path" : "cmake-build-debug/_deps/alpaka-src/cmake/tests/StdAtomicRef.cpp"
		},
		{
			"isCMake" : true,
			"isExternal" : true,
			"path" : "/home/tim/clion/clion-2024.3/bin/cmake/linux/x64/share/cmake-3.30/Modules/CMakePackageConfigHelpers.cmake"
		},
		{
			"isCMake" : true,
			"isExternal" : true,
			"path" : "/home/tim/clion/clion-2024.3/bin/cmake/linux/x64/share/cmake-3.30/Modules/WriteBasicConfigVersionFile.cmake"
		},
		{
			"isCMake" : true,
			"isExternal" : true,
			"path" : "/home/tim/clion/clion-2024.3/bin/cmake/linux/x64/share/cmake-3.30/Modules/GNUInstallDirs.cmake"
		},
		{
			"isCMake" : true,
			"isExternal" : true,
			"path" : "/home/tim/clion/clion-2024.3/bin/cmake/linux/x64/share/cmake-3.30/Modules/BasicConfigVersion-SameMajorVersion.cmake.in"
		},
		{
			"isGenerated" : true,
			"path" : "cmake-build-debug/_deps/alpaka-src/cmake/alpakaConfig.cmake.in"
		},
		{
			"path" : "examples/CMakeLists.txt"
		},
		{
			"path" : "examples/basic/CMakeLists.txt"
		},
		{
			"isGenerated" : true,
			"path" : "cmake-build-debug/CMakeFiles/3.30.5/CMakeCCompiler.cmake"
		},
		{
			"isCMake" : true,
			"isExternal" : true,
			"path" : "/home/tim/clion/clion-2024.3/bin/cmake/linux/x64/share/cmake-3.30/Modules/CMakeCInformation.cmake"
		},
		{
			"isCMake" : true,
			"isExternal" : true,
			"path" : "/home/tim/clion/clion-2024.3/bin/cmake/linux/x64/share/cmake-3.30/Modules/CMakeLanguageInformation.cmake"
		},
		{
			"isCMake" : true,
			"isExternal" : true,
			"path" : "/home/tim/clion/clion-2024.3/bin/cmake/linux/x64/share/cmake-3.30/Modules/Compiler/GNU-C.cmake"
		},
		{
			"isCMake" : true,
			"isExternal" : true,
			"path" : "/home/tim/clion/clion-2024.3/bin/cmake/linux/x64/share/cmake-3.30/Modules/Compiler/GNU.cmake"
		},
		{
			"isCMake" : true,
			"isExternal" : true,
			"path" : "/home/tim/clion/clion-2024.3/bin/cmake/linux/x64/share/cmake-3.30/Modules/Platform/Linux-GNU-C.cmake"
		},
		{
			"isCMake" : true,
			"isExternal" : true,
			"path" : "/home/tim/clion/clion-2024.3/bin/cmake/linux/x64/share/cmake-3.30/Modules/Platform/Linux-GNU.cmake"
		},
		{
			"isCMake" : true,
			"isExternal" : true,
			"path" : "/home/tim/clion/clion-2024.3/bin/cmake/linux/x64/share/cmake-3.30/Modules/CMakeCommonLanguageInclude.cmake"
		},
		{
			"isGenerated" : true,
			"path" : "cmake-build-debug/_deps/alpaka-src/cmake/alpakaPrepareForAddSubdirectoryUsage.cmake"
		},
		{
			"isGenerated" : true,
			"path" : "cmake-build-debug/_deps/alpaka-src/cmake/alpakaCommon.cmake"
		},
		{
			"isGenerated" : true,
			"path" : "cmake-build-debug/_deps/alpaka-src/cmake/buildDependencies.cmake"
		},
		{
			"isGenerated" : true,
			"path" : "cmake-build-debug/_deps/alpaka-src/cmake/finalize.cmake"
		},
		{
			"isGenerated" : true,
			"path" : "cmake-build-debug/_deps/alpaka-src/cmake/common.cmake"
		},
		{
			"isCMake" : true,
			"isExternal" : true,
			"path" : "/home/tim/clion/clion-2024.3/bin/cmake/linux/x64/share/cmake-3.30/Modules/CheckLanguage.cmake"
		},
		{
			"isCMake" : true,
			"isExternal" : true,
			"path" : "/home/tim/clion/clion-2024.3/bin/cmake/linux/x64/share/cmake-3.30/Modules/FindOpenMP.cmake"
		},
		{
			"isCMake" : true,
			"isExternal" : true,
			"path" : "/home/tim/clion/clion-2024.3/bin/cmake/linux/x64/share/cmake-3.30/Modules/CMakeParseImplicitLinkInfo.cmake"
		},
		{
			"isCMake" : true,
			"isExternal" : true,
			"path" : "/home/tim/clion/clion-2024.3/bin/cmake/linux/x64/share/cmake-3.30/Modules/FindPackageHandleStandardArgs.cmake"
		},
		{
			"isCMake" : true,
			"isExternal" : true,
			"path" : "/home/tim/clion/clion-2024.3/bin/cmake/linux/x64/share/cmake-3.30/Modules/FindPackageMessage.cmake"
		},
		{
			"isGenerated" : true,
			"path" : "cmake-build-debug/_deps/alpaka-src/cmake/tests/StdAtomicRef.cpp"
		},
		{
			"isCMake" : true,
			"isExternal" : true,
			"path" : "/home/tim/clion/clion-2024.3/bin/cmake/linux/x64/share/cmake-3.30/Modules/FindOpenMP.cmake"
		},
		{
			"isCMake" : true,
			"isExternal" : true,
			"path" : "/home/tim/clion/clion-2024.3/bin/cmake/linux/x64/share/cmake-3.30/Modules/CMakeParseImplicitLinkInfo.cmake"
		},
		{
			"isCMake" : true,
			"isExternal" : true,
			"path" : "/home/tim/clion/clion-2024.3/bin/cmake/linux/x64/share/cmake-3.30/Modules/FindPackageHandleStandardArgs.cmake"
		},
		{
			"isCMake" : true,
			"isExternal" : true,
			"path" : "/home/tim/clion/clion-2024.3/bin/cmake/linux/x64/share/cmake-3.30/Modules/FindPackageMessage.cmake"
		}
	],
	"kind" : "cmakeFiles",
	"paths" : 
	{
		"build" : "/home/tim/hzdr/workspace/CLUEport/cmake-build-debug",
		"source" : "/home/tim/hzdr/workspace/CLUEport"
	},
	"version" : 
	{
		"major" : 1,
		"minor" : 1
	}
}
